tgrad/__init__.py
tgrad/client.py
tgrad/config.py
tgrad/server.py
tgrad-0.1.2.dist-info/licenses/LICENSE
tgrad-0.1.2.dist-info/METADATA
tgrad-0.1.2.dist-info/WHEEL
tgrad-0.1.2.dist-info/entry_points.txt
tgrad-0.1.2.dist-info/top_level.txt
tgrad-0.1.2.dist-info/RECORD
