Metadata-Version: 2.4
Name: tgrad
Version: 0.1.2
Summary: Lightweight Python-based Telegram daemon for notification
Author-email: Tareq Mahmood <check@my.website>
License: MIT
Requires-Python: >=3.7
License-File: LICENSE
Requires-Dist: python-telegram-bot>=20.0
Dynamic: license-file
